README.md
setup.cfg
setup.py
django_rest_delegated_permissions.egg-info/PKG-INFO
django_rest_delegated_permissions.egg-info/SOURCES.txt
django_rest_delegated_permissions.egg-info/dependency_links.txt
django_rest_delegated_permissions.egg-info/requires.txt
django_rest_delegated_permissions.egg-info/top_level.txt
rest_delegated_permissions/__init__.py
rest_delegated_permissions/permissions.py