Metadata-Version: 1.0
Name: django-rest-delegated-permissions
Version: 1.4.0
Summary: Taking (delegating) REST permissions from a model instance to a model pointed by ForeignKey/m2m
Home-page: https://github.com/mesemus/django-rest-delegated-permissions
Author: Mirek Simek
Author-email: miroslav.simek@gmail.com
License: MIT
Platform: UNKNOWN
